PandasXuexiShouceZhongwenDierBanChuyi/README.md
PandasXuexiShouceZhongwenDierBanChuyi/__init__.py
PandasXuexiShouceZhongwenDierBanChuyi/__main__.py
PandasXuexiShouceZhongwenDierBanChuyi/file.epub
PandasXuexiShouceZhongwenDierBanChuyi/index.html
PandasXuexiShouceZhongwenDierBanChuyi/css/__init__.py
PandasXuexiShouceZhongwenDierBanChuyi/css/annotations.css
PandasXuexiShouceZhongwenDierBanChuyi/css/main.css
PandasXuexiShouceZhongwenDierBanChuyi/css/normalize.css
PandasXuexiShouceZhongwenDierBanChuyi/css/popup.css
PandasXuexiShouceZhongwenDierBanChuyi/font/__init__.py
PandasXuexiShouceZhongwenDierBanChuyi/font/fontello.eot
PandasXuexiShouceZhongwenDierBanChuyi/font/fontello.svg
PandasXuexiShouceZhongwenDierBanChuyi/font/fontello.ttf
PandasXuexiShouceZhongwenDierBanChuyi/font/fontello.woff
PandasXuexiShouceZhongwenDierBanChuyi/img/__init__.py
PandasXuexiShouceZhongwenDierBanChuyi/img/annotator-glyph-sprite.png
PandasXuexiShouceZhongwenDierBanChuyi/img/annotator-icon-sprite.png
PandasXuexiShouceZhongwenDierBanChuyi/img/apple-touch-icon.png
PandasXuexiShouceZhongwenDierBanChuyi/img/cancelfullscreen.png
PandasXuexiShouceZhongwenDierBanChuyi/img/close.png
PandasXuexiShouceZhongwenDierBanChuyi/img/fullscreen.png
PandasXuexiShouceZhongwenDierBanChuyi/img/loader.gif
PandasXuexiShouceZhongwenDierBanChuyi/img/menu-icon.png
PandasXuexiShouceZhongwenDierBanChuyi/img/save.png
PandasXuexiShouceZhongwenDierBanChuyi/img/saved.png
PandasXuexiShouceZhongwenDierBanChuyi/img/settings-s.png
PandasXuexiShouceZhongwenDierBanChuyi/img/settings.png
PandasXuexiShouceZhongwenDierBanChuyi/img/star.png
PandasXuexiShouceZhongwenDierBanChuyi/js/__init__.py
PandasXuexiShouceZhongwenDierBanChuyi/js/epub.js
PandasXuexiShouceZhongwenDierBanChuyi/js/epub.min.js
PandasXuexiShouceZhongwenDierBanChuyi/js/epub.min.map
PandasXuexiShouceZhongwenDierBanChuyi/js/hooks.min.js
PandasXuexiShouceZhongwenDierBanChuyi/js/hooks.min.map
PandasXuexiShouceZhongwenDierBanChuyi/js/reader.js
pandas_xuexi_shouce_zhongwen_dier_ban_chuyi-2024.3.5.0.dist-info/METADATA
pandas_xuexi_shouce_zhongwen_dier_ban_chuyi-2024.3.5.0.dist-info/WHEEL
pandas_xuexi_shouce_zhongwen_dier_ban_chuyi-2024.3.5.0.dist-info/entry_points.txt
pandas_xuexi_shouce_zhongwen_dier_ban_chuyi-2024.3.5.0.dist-info/top_level.txt
pandas_xuexi_shouce_zhongwen_dier_ban_chuyi-2024.3.5.0.dist-info/RECORD
